{
    "characteristics":
        {
            "width": 11,
            "height": 19
        },
    "holdSetup" : { 
        "c1": {"holdColor": "#333"},
        "e1": {"holdColor": "#fff"},
        "g1": {"holdColor": "#333"},
        "h1": {"holdColor": "#fff"},
        "i1": {"holdColor": "#fff"},
        "j1": {"holdColor": "#aaa"},
        "k1": {"holdColor": "#762", "hold": "toni-6", "rotation": -5},

        "a2": {"holdColor": "#762", "hold": "toni-6", "rotation": 45},
        "b2": {"holdColor": "#762"},
        "d2": {"holdColor": "#dca"},
        "e2": {"holdColor": "#aaa"},
        "g2": {"holdColor": "#762"},
        "i2": {"holdColor": "#dca"},

        "d3": {"holdColor": "#333", "hold": "toni-6", "rotation": -5},
        "e3": {"holdColor": "#762", "hold": "toni-6", "rotation": -5},
        "f3": {"holdColor": "#dca"},
        "i3": {"holdColor": "#762", "hold": "toni-6", "rotation": -20},
        "k3": {"holdColor": "#762", "hold": "toni-6", "rotation": 70},

        "a4": {"holdColor": "#aaa", "hold": "toni-kirves", "rotation": 110},
        "d4": {"holdColor": "#dca", "hold": "toni-peruna"},
        "f4": {"holdColor": "#762", "hold": "toni-peruna", "rotation": -20},
        "g4": {"holdColor": "#dca", "hold": "toni-kirves", "rotation": 40},
        "i4": {"holdColor": "#333"},
        "j4": {"holdColor": "#fff"},
        "e4": {"holdColor": "#dca"},

        "b5": {"holdColor": "#fff", "hold": "toni-kahva", "rotation": -20},
        "c5": {"holdColor": "#dca", "hold": "toni-6", "rotation": -50},
        "d5": {"holdColor": "#333", "hold": "toni-kahva", "rotation": 35},
        "f5": {"holdColor": "#aaa", "hold": "toni-kahva", "rotation": 20},
        "i5": {"holdColor": "#dca"},
        "k5": {"holdColor": "#aaa", "hold": "toni-kirves", "rotation": 45},

        "b6": {"holdColor": "#fff", "hold": "toni-5", "rotation": 200},
        "d6": {"holdColor": "#dca", "hold": "toni-peruna", "rotation": -10},
        "g6": {"holdColor": "#dca"},
        "e6": {"holdColor": "#fff", "hold": "toni-6", "rotation": 30},

        "a7": {"holdColor": "#dca"},
        "b7": {"holdColor": "#dca"},
        "c7": {"holdColor": "#dca"},
        "d7": {"holdColor": "#aaa", "hold": "toni-kahva", "rotation": 35},
        "e7": {"holdColor": "#333", "hold": "toni-6", "rotation": -20},
        "f7": {"holdColor": "#dca"},
        "g7": {"holdColor": "#dca", "hold": "toni-6", "rotation": 15},
        "h7": {"holdColor": "#333", "hold": "toni-2"},
        "j7": {"holdColor": "#762", "hold": "toni-kahva", "rotation": 180},
        "k7": {"holdColor": "#762", "hold": "toni-kahva", "rotation": 10},

        "e8": {"holdColor": "#333"},
        "i8": {"holdColor": "#fff", "hold": "toni-5", "rotation": 90},
        "j8": {"holdColor": "#aaa", "hold": "toni-5", "rotation": 0},

        "a9": {"holdColor": "#fff", "hold": "toni-kahva", "rotation": -20},
        "d9": {"holdColor": "#dca"},
        "e9": {"holdColor": "#dca"},


        "a10": {"holdColor": "#762"},
        "b10": {"holdColor": "#fff", "hold": "toni-5", "rotation": 30},
        "c10": {"holdColor": "#dca", "hold": "toni-peruna", "rotation": -80},
        "d10": {"holdColor": "#762"},
        "f10": {"holdColor": "#333", "hold": "toni-kahva", "rotation": 30},
        "g10": {"holdColor": "#333", "hold": "toni-kahva", "rotation": -30},

        "h10": {"holdColor": "#dca"},

        "a11": {"holdColor": "#aaa", "hold": "toni-kahva", "rotation": -20},
        "b11": {"holdColor": "#762"},
        "c11": {"holdColor": "#dca", "hold": "toni-kirves", "rotation": 110},
        "d11": {"holdColor": "#762", "hold": "toni-6", "rotation": 0},
        "f11": {"holdColor": "#333", "hold": "toni-kirves", "rotation": 90},
        "g11": {"holdColor": "#762", "hold": "toni-6", "rotation": 45},
        "h11": {"holdColor": "#dca", "hold": "toni-peruna", "rotation": 110},
        "i11": {"holdColor": "#fff", "hold": "toni-6", "rotation": 50},
        "j11": {"holdColor": "#762", "hold": "toni-6", "rotation": -50},
        "k11": {"holdColor": "#aaa", "hold": "toni-kahva", "rotation": 30},

        "d12": {"holdColor": "#aaa", "hold": "toni-kahva"},
        "e12": {"holdColor": "#fff", "hold": "toni-5", "rotation": -80},
        "h12": {"holdColor": "#fff", "hold": "toni-6"},
        "i12": {"holdColor": "#dca", "hold": "toni-6", "rotation": 50},

        "a13": {"holdColor": "#aaa", "hold": "toni-kirves", "rotation": 130},
        "c13": {"holdColor": "#dca"},
        "d13": {"holdColor": "#762", "hold": "toni-kahva", "rotation": -155},
        "g13": {"holdColor": "#762", "hold": "toni-6"},
        "k13": {"holdColor": "#762", "hold": "toni-kahva", "rotation": 90},

        "a14": {"holdColor": "#dca", "hold": "toni-kahva"},
        "b14": {"holdColor": "#fff"},
        "d14": {"holdColor": "#dca"},
        "e14": {"holdColor": "#dca", "hold": "toni-peruna", "rotation": 110},

        "a15": {"holdColor": "#333", "hold": "toni-kahva", "rotation": -20},
        "c15": {"holdColor": "#dca", "hold": "toni-kahva", "rotation": -20},
        "e15": {"holdColor": "#dca"},
        "f15": {"holdColor": "#dca", "hold": "toni-kahva", "rotation": -30},
        "g15": {"holdColor": "#333", "hold": "toni-kahva", "rotation": 30},
        "h15": {"holdColor": "#aaa", "hold": "toni-kahva", "rotation": -30},
        "j16": {"holdColor": "#333", "hold": "toni-kahva", "rotation": 80},
        "k15": {"holdColor": "#762"},

        "d16": {"holdColor": "#fff"},
        "i16": {"holdColor": "#dca"},

        "a17": {"holdColor": "#fff"},
        "b17": {"holdColor": "#762"},
        "d17": {"holdColor": "#762"},
        "e17": {"holdColor": "#333"},
        "g17": {"holdColor": "#aaa"},
        "h17": {"holdColor": "#333", "hold": "toni-6"},

        "b18": {"holdColor": "#aaa"},
        "h18": {"holdColor": "#762", "hold": "toni-6", "rotation": -45},
        "k18": {"holdColor": "#dca"},
        
        "j19": {"holdColor": "#762"}

    }
}